{
  "ds_number": "5530503",
  "vendor": "CANAL TOYS",
  "brand": "So Slime",
  "vendor_item_number": "277263",
  "product_name": "So Slime DIY Marble Mix & Twist Slime Kit",
  "identity": {
    "id_type": "UPC",
    "upc": "850041019680"
  },
  "pricing": {
    "drop_ship_cost": 24.5,
    "wholesale_cost": 17.3,
    "ds_cost_domestic": null,
    "import_cost": null,
    "msrp": 34.99
  },
  "sourcing": {
    "fob_point": null,
    "country_of_origin": "China",
    "harmonized_code": "9503.00.0073"
  },
  "content": {
    "bullets": [
      "A fun new way to create amazing, marble colored slimes from So Slime",
      "Mix and create your own slime creations using this mixer, premade slime, colorant, and decorations",
      "Fill the bowl and turn to mix it up! It so fun and satisfying to watch",
      "Everything is included  to mix up your slime styles.",
      "Follow the 6 suggested recipes included or make up your own"
    ],
    "keywords": null,
    "description": "A fun new way to create amazing, marble colored slimes from SoSlime! \nMix and create your own slime creations using this mixer, premade slime, colorant, and decorations. \nFill the bowl and turn to mix it up! It so fun and satisfying to watch! Everything is include to mix up your slime styles.\nFollow the 6 suggested recipes included or make up your own!\nIncludes mixer station, mixing bowl, 6 bags of premade white slime, 6 bags of colorant powder, 6 styles decorations, 1 sticker label sheet, mixing guide and instruction manual"
  },
  "attributes": {
    "material": "plastic, slime, paper",
    "num_pieces": "22 pieces",
    "whats_in_box": "mixer station, mixing bowl, 6 bags of premade white slime, 6 bags of colorant powder, 6 styles decorations, 1 sticker label sheet, mixing guide and instruction manual",
    "primary_color": "Multi",
    "secondary_color": null,
    "min_age": 6,
    "max_age": 0,
    "gender": null,
    "assembly_required": "No",
    "assembly_instructions": null
  },
  "images": {
    "availability": "Yes",
    "urls": [
      "https://m.media-amazon.com/images/I/813NHObZnyL.jpg",
      "https://m.media-amazon.com/images/I/81XvEi-8G4L.jpg",
      "https://m.media-amazon.com/images/I/81fTY4BqdrL.jpg",
      "https://m.media-amazon.com/images/I/810yVN4ogyL.jpg",
      "https://m.media-amazon.com/images/I/81+qyILn2QL.jpg",
      "https://m.media-amazon.com/images/I/81QOhqLIN7L.jpg",
      "https://m.media-amazon.com/images/I/81dCE3OlC6L.jpg",
      "https://m.media-amazon.com/images/I/81+vEDpvhsL.jpg",
      "https://m.media-amazon.com/images/I/71Kl7N1KI7L.jpg",
      "https://m.media-amazon.com/images/I/71rpKhzsfeL.jpg"
    ]
  },
  "dimensions": {
    "item": {
      "weight": 2.6,
      "weight_unit": "lbs",
      "length": 13.38,
      "length_unit": "in",
      "width": 5.51,
      "width_unit": "in",
      "height": 12.25,
      "height_unit": "in"
    },
    "package": {
      "weight": 2.6,
      "weight_unit": "lbs",
      "length": 13.38,
      "length_unit": "in",
      "width": 5.51,
      "width_unit": "in",
      "height": 12.25,
      "height_unit": "in"
    },
    "master_case": {
      "case_qty": 4,
      "length": 17.52,
      "length_unit": "in",
      "width": 14,
      "width_unit": "in",
      "height": 11.42,
      "height_unit": "in",
      "weight": 12,
      "weight_unit": "lbs"
    }
  },
  "compliance": {
    "choking_hazard": "Yes",
    "lead_phthalates": null,
    "warranty_included": "No",
    "warranty_desc": null,
    "batteries_required": "No",
    "batteries_included": null,
    "battery_cell_comp": null,
    "battery_type_qty": null,
    "packaging_type": null,
    "compliance_cert": null,
    "doc": null,
    "sds": null,
    "sds_url": null,
    "cpsia": null,
    "test_reports": null,
    "cpc": null,
    "product_pics": null,
    "instructions": null,
    "letter_of_compliance": null
  },
  "_meta": {
    "source_file": "Canal Toys New Item Setup Sheet Template Version 2025 3.25.26.xlsx",
    "imported_at": "2026-06-22",
    "supplier_id": null,
    "last_verified": null,
    "source_sheet": "DS Only",
    "vendor_slug": "canal-toys"
  }
}
